LICENSE
MANIFEST.in
README.rst
setup.py
django_easy_contact.egg-info/PKG-INFO
django_easy_contact.egg-info/SOURCES.txt
django_easy_contact.egg-info/dependency_links.txt
django_easy_contact.egg-info/not-zip-safe
django_easy_contact.egg-info/top_level.txt
easy_contact/__init__.py
easy_contact/__init__.pyc
easy_contact/cf_settings.py
easy_contact/forms.py
easy_contact/forms.pyc
easy_contact/urls.py
easy_contact/urls.pyc
easy_contact/version.py
easy_contact/version.pyc
easy_contact/views.py
easy_contact/views.pyc
easy_contact/views_1.py
easy_contact/views_2.py
easy_contact/locale/de/LC_MESSAGES/django.mo
easy_contact/locale/de/LC_MESSAGES/django.po
easy_contact/locale/en/LC_MESSAGES/django.mo
easy_contact/locale/en/LC_MESSAGES/django.po
easy_contact/locale/zh/LC_MESSAGES/django.mo
easy_contact/locale/zh/LC_MESSAGES/django.po
easy_contact/templates/easy_contact/contact.html
easy_contact/templates/easy_contact/success.html