Metadata-Version: 1.1
Name: django-easy-contact
Version: 0.3.8
Summary: A simple contact form application.
Home-page: https://bitbucket.org/catapela/django-easy-contact
Author: Andreas Fritz, digital.elements.li
Author-email: easy-contact@bitzeit.eu
License: BSD
Download-URL: https://pypi.python.org/pypi/django-easy-contact
Keywords: django mail configuration setup mailform
Platform: UNKNOWN
Classifier: Development Status :: 4 - Beta
Classifier: Framework :: Django
Classifier: License :: OSI Approved :: BSD License
Classifier: Operating System :: OS Independent
Classifier: Programming Language :: Python
Classifier: Environment :: Console
Classifier: Natural Language :: English
Classifier: Natural Language :: German
Classifier: Intended Audience :: Developers
Classifier: Intended Audience :: Information Technology
Classifier: Topic :: Internet
Classifier: Topic :: Utilities
